spokenpy/__init__.py
spokenpy/cli.py
spokenpy/core.py
spokenpy-0.1.3.dist-info/licenses/LICENSE
spokenpy-0.1.3.dist-info/METADATA
spokenpy-0.1.3.dist-info/WHEEL
spokenpy-0.1.3.dist-info/entry_points.txt
spokenpy-0.1.3.dist-info/top_level.txt
spokenpy-0.1.3.dist-info/RECORD
